<?xml version="1.0" encoding="UTF-8"?><NOTICE id="0765612" type="UNI:100"><champs UnimarcTag="019"><SOUSCHAMP UnimarcSubfield="019$"><data>  </data></SOUSCHAMP><SOUSCHAMP UnimarcSubfield="019$a"><data>UNI100</data></SOUSCHAMP><SOUSCHAMP UnimarcSubfield="019$b"><data>4091</data></SOUSCHAMP></champs><champs UnimarcTag="200"><SOUSCHAMP UnimarcSubfield="200$"><data>| </data></SOUSCHAMP><SOUSCHAMP UnimarcSubfield="200$a"><data>Quatuor à cordes no 3</data></SOUSCHAMP><SOUSCHAMP UnimarcSubfield="200$f"><data>Alexander von Zemlinsky</data></SOUSCHAMP></champs><champs UnimarcTag="500"><SOUSCHAMP UnimarcSubfield="500$"><data>|1</data></SOUSCHAMP><SOUSCHAMP UnimarcSubfield="500$3"><data>0765595</data></SOUSCHAMP><SOUSCHAMP UnimarcSubfield="500$a"><data>Quatuors</data></SOUSCHAMP><SOUSCHAMP UnimarcSubfield="500$r"><data>Cordes</data></SOUSCHAMP><SOUSCHAMP UnimarcSubfield="500$s"><data>Op. 19</data></SOUSCHAMP><SOUSCHAMP UnimarcSubfield="500$n"><data>No 3</data></SOUSCHAMP></champs><champs UnimarcTag="610"><SOUSCHAMP UnimarcSubfield="610$"><data>  </data></SOUSCHAMP><SOUSCHAMP UnimarcSubfield="610$3"><data>0067730</data></SOUSCHAMP><SOUSCHAMP UnimarcSubfield="610$a"><data>20 ème siècle - 1 ère moitié</data></SOUSCHAMP><SOUSCHAMP UnimarcSubfield="610$b"><data>02</data></SOUSCHAMP></champs><champs UnimarcTag="610"><SOUSCHAMP UnimarcSubfield="610$"><data>  </data></SOUSCHAMP><SOUSCHAMP UnimarcSubfield="610$3"><data>0068827</data></SOUSCHAMP><SOUSCHAMP UnimarcSubfield="610$a"><data>Quatuor à cordes</data></SOUSCHAMP></champs><champs UnimarcTag="700"><SOUSCHAMP UnimarcSubfield="700$"><data> |</data></SOUSCHAMP><SOUSCHAMP UnimarcSubfield="700$3"><data>0035722</data></SOUSCHAMP><SOUSCHAMP UnimarcSubfield="700$a"><data>Zemlinsky</data></SOUSCHAMP><SOUSCHAMP UnimarcSubfield="700$b"><data>Alexander von</data></SOUSCHAMP><SOUSCHAMP UnimarcSubfield="700$f"><data>1871-1942</data></SOUSCHAMP><SOUSCHAMP UnimarcSubfield="700$4"><data>230</data></SOUSCHAMP></champs><champs UnimarcTag="830"><SOUSCHAMP UnimarcSubfield="830$"><data>  </data></SOUSCHAMP><SOUSCHAMP UnimarcSubfield="830$a"><data>Source : Fayard, Guide de la musique de chambre, 1989</data></SOUSCHAMP></champs><champs UnimarcTag="909"><SOUSCHAMP UnimarcSubfield="909$"><data>  </data></SOUSCHAMP><SOUSCHAMP UnimarcSubfield="909$a"><data>Comprend : Allegro, Thema mit Variationen, Romanze, Burleske. durée : 23-25 mn. Dédié à Friedrich Buxbaum</data></SOUSCHAMP><SOUSCHAMP UnimarcSubfield="909$b"><data>1924</data></SOUSCHAMP><SOUSCHAMP UnimarcSubfield="909$c"><data>2 violons, alto, violoncelle</data></SOUSCHAMP><SOUSCHAMP UnimarcSubfield="909$e"><data>Op. 19</data></SOUSCHAMP><SOUSCHAMP UnimarcSubfield="909$g"><data>1924</data></SOUSCHAMP><SOUSCHAMP UnimarcSubfield="909$h"><data>1924</data></SOUSCHAMP></champs><champs UnimarcTag="919"><SOUSCHAMP UnimarcSubfield="919$"><data>  </data></SOUSCHAMP><SOUSCHAMP UnimarcSubfield="919$a"><data>Création à Leipzig, octobre 1925, par le Buxbaum Streichquartett. Première édition le 30 juillet 1930.</data></SOUSCHAMP></champs><champs UnimarcTag="938"><SOUSCHAMP UnimarcSubfield="938$"><data>  </data></SOUSCHAMP><SOUSCHAMP UnimarcSubfield="938$3"><data>0079526</data></SOUSCHAMP><SOUSCHAMP UnimarcSubfield="938$a"><data>Quatuor n° 3 : opus 19 / Alexander von Zemlinsky, composition ; Quatuor Diotima, 25 min 41 sec</data></SOUSCHAMP><SOUSCHAMP UnimarcSubfield="938$b"><data>UNI42</data></SOUSCHAMP></champs><champs UnimarcTag="938"><SOUSCHAMP UnimarcSubfield="938$"><data>  </data></SOUSCHAMP><SOUSCHAMP UnimarcSubfield="938$3"><data>0753776</data></SOUSCHAMP><SOUSCHAMP UnimarcSubfield="938$a"><data>Le IIIe Reich et la musique - Richard Strauss, l'Ecole de Vienne : du samedi 13 au mercredi 24 novembre 2004 / [Auteurs divers], [pag. mult.]</data></SOUSCHAMP><SOUSCHAMP UnimarcSubfield="938$b"><data>UNI1</data></SOUSCHAMP></champs><champs UnimarcTag="938"><SOUSCHAMP UnimarcSubfield="938$"><data>  </data></SOUSCHAMP><SOUSCHAMP UnimarcSubfield="938$3"><data>0773648</data></SOUSCHAMP><SOUSCHAMP UnimarcSubfield="938$a"><data>Quatuor no 3, op. 19 / Alexandre von Zemlinsky ; Solistes de l'Ensemble Intercontemporain, 24 min 32 sec</data></SOUSCHAMP><SOUSCHAMP UnimarcSubfield="938$b"><data>UNI42C</data></SOUSCHAMP></champs><champs UnimarcTag="938"><SOUSCHAMP UnimarcSubfield="938$"><data>  </data></SOUSCHAMP><SOUSCHAMP UnimarcSubfield="938$3"><data>0981978</data></SOUSCHAMP><SOUSCHAMP UnimarcSubfield="938$a"><data>5e Biennale de Quatuors à cordes - Zemlinsky Quartet : dimanche 15 janvier 2012 - 14h30 / Bernard Fournier, François-Gildas Tual, Emmanuel Hondré, 11 p.</data></SOUSCHAMP><SOUSCHAMP UnimarcSubfield="938$b"><data>UNI1</data></SOUSCHAMP></champs><champs UnimarcTag="938"><SOUSCHAMP UnimarcSubfield="938$"><data>  </data></SOUSCHAMP><SOUSCHAMP UnimarcSubfield="938$3"><data>0984505</data></SOUSCHAMP><SOUSCHAMP UnimarcSubfield="938$a"><data>Quatuor à cordes no 3 op. 19 / Alexander von Zemlinsky ; Zemlinsky Quartet ; Frantisek Soucek, Petr Strízek, violons ; Petr Holman, alto ; Vladimír Fortin, violoncelle, 23 min 15 sec</data></SOUSCHAMP><SOUSCHAMP UnimarcSubfield="938$b"><data>UNI42C</data></SOUSCHAMP></champs></NOTICE>