<?xml version="1.0" encoding="UTF-8"?><NOTICE id="0182907" type="UNI:100"><champs UnimarcTag="019"><SOUSCHAMP UnimarcSubfield="019$"><data>  </data></SOUSCHAMP><SOUSCHAMP UnimarcSubfield="019$a"><data>UNI100</data></SOUSCHAMP><SOUSCHAMP UnimarcSubfield="019$b"><data>57427</data></SOUSCHAMP></champs><champs UnimarcTag="200"><SOUSCHAMP UnimarcSubfield="200$"><data>| </data></SOUSCHAMP><SOUSCHAMP UnimarcSubfield="200$a"><data>Ariane à Naxos</data></SOUSCHAMP><SOUSCHAMP UnimarcSubfield="200$f"><data>Richard Strauss</data></SOUSCHAMP></champs><champs UnimarcTag="500"><SOUSCHAMP UnimarcSubfield="500$"><data>|1</data></SOUSCHAMP><SOUSCHAMP UnimarcSubfield="500$3"><data>0747028</data></SOUSCHAMP><SOUSCHAMP UnimarcSubfield="500$a"><data>Ariadne auf Naxos</data></SOUSCHAMP></champs><champs UnimarcTag="610"><SOUSCHAMP UnimarcSubfield="610$"><data>  </data></SOUSCHAMP><SOUSCHAMP UnimarcSubfield="610$3"><data>0064624</data></SOUSCHAMP><SOUSCHAMP UnimarcSubfield="610$a"><data>Opéra</data></SOUSCHAMP><SOUSCHAMP UnimarcSubfield="610$b"><data>04</data></SOUSCHAMP></champs><champs UnimarcTag="610"><SOUSCHAMP UnimarcSubfield="610$"><data>  </data></SOUSCHAMP><SOUSCHAMP UnimarcSubfield="610$3"><data>0067730</data></SOUSCHAMP><SOUSCHAMP UnimarcSubfield="610$a"><data>20 ème siècle - 1 ère moitié</data></SOUSCHAMP><SOUSCHAMP UnimarcSubfield="610$b"><data>02</data></SOUSCHAMP></champs><champs UnimarcTag="700"><SOUSCHAMP UnimarcSubfield="700$"><data> |</data></SOUSCHAMP><SOUSCHAMP UnimarcSubfield="700$3"><data>0048854</data></SOUSCHAMP><SOUSCHAMP UnimarcSubfield="700$a"><data>Strauss</data></SOUSCHAMP><SOUSCHAMP UnimarcSubfield="700$b"><data>Richard</data></SOUSCHAMP><SOUSCHAMP UnimarcSubfield="700$f"><data>1864-1949</data></SOUSCHAMP><SOUSCHAMP UnimarcSubfield="700$4"><data>230</data></SOUSCHAMP></champs><champs UnimarcTag="701"><SOUSCHAMP UnimarcSubfield="701$"><data> |</data></SOUSCHAMP><SOUSCHAMP UnimarcSubfield="701$3"><data>0051620</data></SOUSCHAMP><SOUSCHAMP UnimarcSubfield="701$a"><data>Hofmannsthal</data></SOUSCHAMP><SOUSCHAMP UnimarcSubfield="701$b"><data>Hugo von</data></SOUSCHAMP><SOUSCHAMP UnimarcSubfield="701$f"><data>1874-1929</data></SOUSCHAMP><SOUSCHAMP UnimarcSubfield="701$4"><data>480</data></SOUSCHAMP></champs><champs UnimarcTag="830"><SOUSCHAMP UnimarcSubfield="830$"><data>  </data></SOUSCHAMP><SOUSCHAMP UnimarcSubfield="830$a"><data>BNF Catalogue général 2012/12/12</data></SOUSCHAMP></champs><champs UnimarcTag="909"><SOUSCHAMP UnimarcSubfield="909$"><data>  </data></SOUSCHAMP><SOUSCHAMP UnimarcSubfield="909$a"><data>Opéra en 1 acte et 1 prologue composé sur un livret de Hugo von Hofmannsthal. Il existe une version de 1912, sans le prologue. L'oeuvre a été révisée définitivement en 1916</data></SOUSCHAMP><SOUSCHAMP UnimarcSubfield="909$b"><data>Dates de composition : 1911-1912, 2ème version : 1916.</data></SOUSCHAMP><SOUSCHAMP UnimarcSubfield="909$c"><data>Rôles : La prima donna/Ariane, Zerbinette, une naïade, Écho (Sopranos) ; le compositeur (Mezzo-soprano) ; une dryade (Alto) ; le ténor/Bacchus, Scaramouche, Brighella, le maître de danse, un officier (Ténors) ; Arlequin, le maître de musique, le perruquier (Baryton) ; Truffaldino, le laquais (Basse) ; le majordome (rôle parlé)</data></SOUSCHAMP><SOUSCHAMP UnimarcSubfield="909$e"><data>Op. 60</data></SOUSCHAMP><SOUSCHAMP UnimarcSubfield="909$f"><data>TrV 228</data></SOUSCHAMP><SOUSCHAMP UnimarcSubfield="909$g"><data>1912</data></SOUSCHAMP><SOUSCHAMP UnimarcSubfield="909$h"><data>1916</data></SOUSCHAMP></champs><champs UnimarcTag="919"><SOUSCHAMP UnimarcSubfield="919$"><data>  </data></SOUSCHAMP><SOUSCHAMP UnimarcSubfield="919$a"><data>Créé à Vienne, Hofoper, le 4 octobre 1916</data></SOUSCHAMP></champs><champs UnimarcTag="937"><SOUSCHAMP UnimarcSubfield="937$"><data>  </data></SOUSCHAMP><SOUSCHAMP UnimarcSubfield="937$3"><data>0073955</data></SOUSCHAMP><SOUSCHAMP UnimarcSubfield="937$a"><data>Ariane à Naxos, Strauss : Opéra et mythe (8) / [Auteurs divers], 161 p.</data></SOUSCHAMP><SOUSCHAMP UnimarcSubfield="937$b"><data>UNI1</data></SOUSCHAMP></champs><champs UnimarcTag="937"><SOUSCHAMP UnimarcSubfield="937$"><data>  </data></SOUSCHAMP><SOUSCHAMP UnimarcSubfield="937$3"><data>0074924</data></SOUSCHAMP><SOUSCHAMP UnimarcSubfield="937$a"><data>Ariadne auf Naxos, Richard Strauss / [Auteurs divers] ; Directeur de la publication : Rudolf Berger, 128 p.</data></SOUSCHAMP><SOUSCHAMP UnimarcSubfield="937$b"><data>UNI1</data></SOUSCHAMP></champs><champs UnimarcTag="937"><SOUSCHAMP UnimarcSubfield="937$"><data>  </data></SOUSCHAMP><SOUSCHAMP UnimarcSubfield="937$3"><data>0086480</data></SOUSCHAMP><SOUSCHAMP UnimarcSubfield="937$a"><data>Ariadne auf Naxos / Richard Strauss ; Members of the Opera Chorus Studio of the Sächsische Staatsoper Dresden, Sir Colin Davis, dir., 1 DVD (130 min)</data></SOUSCHAMP><SOUSCHAMP UnimarcSubfield="937$b"><data>UNI4</data></SOUSCHAMP></champs><champs UnimarcTag="937"><SOUSCHAMP UnimarcSubfield="937$"><data>  </data></SOUSCHAMP><SOUSCHAMP UnimarcSubfield="937$3"><data>0779404</data></SOUSCHAMP><SOUSCHAMP UnimarcSubfield="937$a"><data>Ariadne auf Naxos (Ariane à Naxos) : Richard Strauss / Opéra de Paris, 120 p.</data></SOUSCHAMP><SOUSCHAMP UnimarcSubfield="937$b"><data>UNI1</data></SOUSCHAMP></champs><champs UnimarcTag="937"><SOUSCHAMP UnimarcSubfield="937$"><data>  </data></SOUSCHAMP><SOUSCHAMP UnimarcSubfield="937$3"><data>0834581</data></SOUSCHAMP><SOUSCHAMP UnimarcSubfield="937$a"><data>Richard Strauss, mode d'emploi / Christian Merlin, 189 p.</data></SOUSCHAMP><SOUSCHAMP UnimarcSubfield="937$b"><data>UNI1</data></SOUSCHAMP></champs><champs UnimarcTag="937"><SOUSCHAMP UnimarcSubfield="937$"><data>  </data></SOUSCHAMP><SOUSCHAMP UnimarcSubfield="937$3"><data>0891811</data></SOUSCHAMP><SOUSCHAMP UnimarcSubfield="937$a"><data>Richard Strauss : Le Bourgeois gentilhomme, Ariane à Naxos / Opéra de Lyon, 46 p.</data></SOUSCHAMP><SOUSCHAMP UnimarcSubfield="937$b"><data>UNI1</data></SOUSCHAMP></champs><champs UnimarcTag="937"><SOUSCHAMP UnimarcSubfield="937$"><data>  </data></SOUSCHAMP><SOUSCHAMP UnimarcSubfield="937$3"><data>0893182</data></SOUSCHAMP><SOUSCHAMP UnimarcSubfield="937$a"><data>Essai sur l'art lyrique : opéra, merveilleuse douleur / Marie-Françoise Vieuille ; [préface de Philippe Simon], 1 vol. (524 p.)</data></SOUSCHAMP><SOUSCHAMP UnimarcSubfield="937$b"><data>UNI1</data></SOUSCHAMP></champs><champs UnimarcTag="937"><SOUSCHAMP UnimarcSubfield="937$"><data>  </data></SOUSCHAMP><SOUSCHAMP UnimarcSubfield="937$3"><data>0893520</data></SOUSCHAMP><SOUSCHAMP UnimarcSubfield="937$a"><data>L' opéra selon Richard Strauss : un théâtre et son temps / Bernard Banoun, 577 p.</data></SOUSCHAMP><SOUSCHAMP UnimarcSubfield="937$b"><data>UNI1</data></SOUSCHAMP></champs><champs UnimarcTag="937"><SOUSCHAMP UnimarcSubfield="937$"><data>  </data></SOUSCHAMP><SOUSCHAMP UnimarcSubfield="937$3"><data>1021486</data></SOUSCHAMP><SOUSCHAMP UnimarcSubfield="937$a"><data>Ariane à Naxos, Richard Strauss : livret bilingue, guide d'écoute, les sources et les enjeux, les deux versions d'Ariane, discographie-vidéographie, entretien avec Sophie Koch / Auteurs divers, p. 3-155</data></SOUSCHAMP><SOUSCHAMP UnimarcSubfield="937$b"><data>UNI43</data></SOUSCHAMP></champs><champs UnimarcTag="938"><SOUSCHAMP UnimarcSubfield="938$"><data>  </data></SOUSCHAMP><SOUSCHAMP UnimarcSubfield="938$3"><data>0083463</data></SOUSCHAMP><SOUSCHAMP UnimarcSubfield="938$a"><data>Ariadne auf Naxos : Oper in einem Akt mit Prolog / Richard Strauss ; libretto : Hugo von Hofmannsthal ; Philharmonia orchestra ; conducted by Herbert von Karajan, 2 cd (1h 02min, 1h 06min.)</data></SOUSCHAMP><SOUSCHAMP UnimarcSubfield="938$b"><data>UNI2</data></SOUSCHAMP></champs><champs UnimarcTag="938"><SOUSCHAMP UnimarcSubfield="938$"><data>  </data></SOUSCHAMP><SOUSCHAMP UnimarcSubfield="938$3"><data>0183926</data></SOUSCHAMP><SOUSCHAMP UnimarcSubfield="938$a"><data>Ariane auf Naxos Op.60 (II) : Oper in einem Aufzuge. Studien-Partitur : Opera in One Act with a prologue / Richard Strauss ; Prologue by Hugo von Hofmannsthal, 1 conducteur (303 p.)</data></SOUSCHAMP><SOUSCHAMP UnimarcSubfield="938$b"><data>UNI5</data></SOUSCHAMP></champs></NOTICE>