<?xml version="1.0" encoding="UTF-8"?><NOTICE id="0909360" type="UNI:100"><champs UnimarcTag="019"><SOUSCHAMP UnimarcSubfield="019$"><data>  </data></SOUSCHAMP><SOUSCHAMP UnimarcSubfield="019$a"><data>UNI100</data></SOUSCHAMP></champs><champs UnimarcTag="100"><SOUSCHAMP UnimarcSubfield="100$"><data>  </data></SOUSCHAMP><SOUSCHAMP UnimarcSubfield="100$a"><data>20050527d||||    uuuy0frey0103    ba</data></SOUSCHAMP></champs><champs UnimarcTag="200"><SOUSCHAMP UnimarcSubfield="200$"><data>| </data></SOUSCHAMP><SOUSCHAMP UnimarcSubfield="200$a"><data>Sonate en trio à quatre parties no 10</data></SOUSCHAMP><SOUSCHAMP UnimarcSubfield="200$f"><data>Henry Purcell</data></SOUSCHAMP></champs><champs UnimarcTag="500"><SOUSCHAMP UnimarcSubfield="500$"><data>|1</data></SOUSCHAMP><SOUSCHAMP UnimarcSubfield="500$3"><data>0909349</data></SOUSCHAMP><SOUSCHAMP UnimarcSubfield="500$a"><data>Sonates</data></SOUSCHAMP><SOUSCHAMP UnimarcSubfield="500$u"><data>Ré majeur</data></SOUSCHAMP></champs><champs UnimarcTag="610"><SOUSCHAMP UnimarcSubfield="610$"><data>  </data></SOUSCHAMP><SOUSCHAMP UnimarcSubfield="610$3"><data>0068866</data></SOUSCHAMP><SOUSCHAMP UnimarcSubfield="610$a"><data>Musique de chambre</data></SOUSCHAMP><SOUSCHAMP UnimarcSubfield="610$b"><data>04</data></SOUSCHAMP></champs><champs UnimarcTag="610"><SOUSCHAMP UnimarcSubfield="610$"><data>  </data></SOUSCHAMP><SOUSCHAMP UnimarcSubfield="610$3"><data>0145869</data></SOUSCHAMP><SOUSCHAMP UnimarcSubfield="610$a"><data>17 ème siècle</data></SOUSCHAMP><SOUSCHAMP UnimarcSubfield="610$b"><data>02</data></SOUSCHAMP></champs><champs UnimarcTag="610"><SOUSCHAMP UnimarcSubfield="610$"><data>  </data></SOUSCHAMP><SOUSCHAMP UnimarcSubfield="610$3"><data>0067509</data></SOUSCHAMP><SOUSCHAMP UnimarcSubfield="610$a"><data>Musique baroque</data></SOUSCHAMP></champs><champs UnimarcTag="700"><SOUSCHAMP UnimarcSubfield="700$"><data> 1</data></SOUSCHAMP><SOUSCHAMP UnimarcSubfield="700$3"><data>0035234</data></SOUSCHAMP><SOUSCHAMP UnimarcSubfield="700$a"><data>Purcell</data></SOUSCHAMP><SOUSCHAMP UnimarcSubfield="700$b"><data>Henry</data></SOUSCHAMP><SOUSCHAMP UnimarcSubfield="700$f"><data>1659-1695</data></SOUSCHAMP><SOUSCHAMP UnimarcSubfield="700$4"><data>230</data></SOUSCHAMP></champs><champs UnimarcTag="830"><SOUSCHAMP UnimarcSubfield="830$"><data>  </data></SOUSCHAMP><SOUSCHAMP UnimarcSubfield="830$a"><data>BN OPALE-PLUS 2009/06/25</data></SOUSCHAMP></champs><champs UnimarcTag="909"><SOUSCHAMP UnimarcSubfield="909$"><data>  </data></SOUSCHAMP><SOUSCHAMP UnimarcSubfield="909$a"><data>Dans ses sonates pour violon, notamment les Ten Sonatas in four parts dont est extraite cette sonate, Purcell rompt avec la tradition pour se tourner vers le nouveau style importé d'Italie ; le violon prend alors le pas sur la viole. La veuve de Purcell fait paraître en 1697 ces dix sonates à quatre parties et les dédie à Lady Rhodia Cavendish, ancienne élève de son mari.</data></SOUSCHAMP><SOUSCHAMP UnimarcSubfield="909$b"><data>vers 1680.</data></SOUSCHAMP><SOUSCHAMP UnimarcSubfield="909$c"><data>2 violons, basse de viole et basse continue.</data></SOUSCHAMP><SOUSCHAMP UnimarcSubfield="909$d"><data>Ré majeur</data></SOUSCHAMP><SOUSCHAMP UnimarcSubfield="909$f"><data>Z 811</data></SOUSCHAMP><SOUSCHAMP UnimarcSubfield="909$g"><data>1678</data></SOUSCHAMP><SOUSCHAMP UnimarcSubfield="909$h"><data>1683</data></SOUSCHAMP></champs><champs UnimarcTag="919"><SOUSCHAMP UnimarcSubfield="919$"><data>  </data></SOUSCHAMP><SOUSCHAMP UnimarcSubfield="919$a"><data>Première publication : Londres, 1697</data></SOUSCHAMP></champs><champs UnimarcTag="938"><SOUSCHAMP UnimarcSubfield="938$"><data>  </data></SOUSCHAMP><SOUSCHAMP UnimarcSubfield="938$3"><data>0909175</data></SOUSCHAMP><SOUSCHAMP UnimarcSubfield="938$a"><data>Intégrale de la musique de chambre. CD 2, Dix sonates en quatre parties (1697) / Henry Purcell, compositeur ; Pieter-Jan Belder, clavecin ; Musica Amphion, ensemble, ...[et al.], 1 cd (1h 19 min)</data></SOUSCHAMP><SOUSCHAMP UnimarcSubfield="938$b"><data>UNI2</data></SOUSCHAMP></champs></NOTICE>